terai/GroqApi.py
terai/__init__.py
terai/main.py
terai-1.0.0.dist-info/LICENSE
terai-1.0.0.dist-info/METADATA
terai-1.0.0.dist-info/WHEEL
terai-1.0.0.dist-info/entry_points.txt
terai-1.0.0.dist-info/RECORD
