Metadata-Version: 2.3
Name: terai
Version: 1.0.0
Summary: A terminal-based AI assistant that translates natural language queries into shell commands and executes them directly. Users can interact naturally, such as by typing "create me a Docker container," and the AI will generate, display, and run the appropriate command.
Author: Sahil Gupta
Requires-Python: >=3.12,<4.0
Classifier: Programming Language :: Python :: 3
Classifier: Programming Language :: Python :: 3.12
Classifier: Programming Language :: Python :: 3.13
Requires-Dist: flake8 (>=7.1.1,<8.0.0)
Requires-Dist: groq (>=0.15.0,<0.16.0)
